browserxt-0.2.3.dist-info/METADATA
browserxt-0.2.3.dist-info/WHEEL
browserxt-0.2.3.dist-info/entry_points.txt
browserxt-0.2.3.dist-info/licenses/LICENSE
browserxt/__init__.py
browserxt/browser.py
browserxt/cli.py
browserxt/constants.py
browserxt/globals.py
browserxt/profiles.py
browserxt/py.typed
browserxt/settings.py
browserxt/utils.py
browserxt-0.2.3.dist-info/RECORD
