Metadata-Version: 2.1
Name: browserxt
Version: 0.2.3
Summary: A simple extensible browser runner
Keywords: copier-template,full-development-lifecycle,project-template,serious-scaffold,winreg; sys_platform == 'win32'
License: MPL-2.0
Project-URL: Documentation, https://browserxt.punkops.dev
Project-URL: Issue, https://github.com/punkops/browserxt/issues
Project-URL: Repository, https://github.com/punkops/browserxt
Requires-Python: >=3.11
Requires-Dist: pydantic-settings
Requires-Dist: typer[all]
